chatgpt_tool_hub/__init__.py
chatgpt_tool_hub/version.py
chatgpt_tool_hub/apps/__init__.py
chatgpt_tool_hub/apps/app.py
chatgpt_tool_hub/apps/app_factory.py
chatgpt_tool_hub/apps/lite_app.py
chatgpt_tool_hub/apps/victorinox.py
chatgpt_tool_hub/bots/__init__.py
chatgpt_tool_hub/bots/all_bot_list.py
chatgpt_tool_hub/bots/chat_bot/__init__.py
chatgpt_tool_hub/bots/chat_bot/base.py
chatgpt_tool_hub/bots/chat_bot/prompt.py
chatgpt_tool_hub/bots/qa_bot/__init__.py
chatgpt_tool_hub/bots/qa_bot/base.py
chatgpt_tool_hub/bots/qa_bot/prompt.py
chatgpt_tool_hub/chains/__init__.py
chatgpt_tool_hub/chains/base.py
chatgpt_tool_hub/chains/llm.py
chatgpt_tool_hub/chains/api/__init__.py
chatgpt_tool_hub/chains/api/base.py
chatgpt_tool_hub/chains/api/prompt.py
chatgpt_tool_hub/common/__init__.py
chatgpt_tool_hub/common/cache.py
chatgpt_tool_hub/common/calculate_token.py
chatgpt_tool_hub/common/callbacks.py
chatgpt_tool_hub/common/config.py
chatgpt_tool_hub/common/constants.py
chatgpt_tool_hub/common/document.py
chatgpt_tool_hub/common/formatting.py
chatgpt_tool_hub/common/input.py
chatgpt_tool_hub/common/json_utils.py
chatgpt_tool_hub/common/log.py
chatgpt_tool_hub/common/schema.py
chatgpt_tool_hub/common/singleton.py
chatgpt_tool_hub/common/text_splitter.py
chatgpt_tool_hub/common/utils.py
chatgpt_tool_hub/database/__init__.py
chatgpt_tool_hub/database/chat_memory.py
chatgpt_tool_hub/database/token_buffer.py
chatgpt_tool_hub/database/utils.py
chatgpt_tool_hub/engine/__init__.py
chatgpt_tool_hub/engine/bot.py
chatgpt_tool_hub/engine/initialize.py
chatgpt_tool_hub/engine/tool_engine.py
chatgpt_tool_hub/models/__init__.py
chatgpt_tool_hub/models/base.py
chatgpt_tool_hub/models/model_factory.py
chatgpt_tool_hub/models/chatgpt/__init__.py
chatgpt_tool_hub/models/chatgpt/base.py
chatgpt_tool_hub/models/chatgpt/chatgpt.py
chatgpt_tool_hub/prompts/__init__.py
chatgpt_tool_hub/prompts/base.py
chatgpt_tool_hub/prompts/chat.py
chatgpt_tool_hub/prompts/prompt.py
wqj_chatgpt_tool_hub-0.4.8.dist-info/LICENSE
wqj_chatgpt_tool_hub-0.4.8.dist-info/METADATA
wqj_chatgpt_tool_hub-0.4.8.dist-info/WHEEL
wqj_chatgpt_tool_hub-0.4.8.dist-info/top_level.txt
wqj_chatgpt_tool_hub-0.4.8.dist-info/RECORD
