Metadata-Version: 2.1
Name: wqj-chatgpt-tool-hub
Version: 0.4.8
Summary: An open-source chatgpt tool ecosystem where you can combine tools with chatgpt and use natural language to do anything.
Home-page: https://github.com/wqjuser/wqj-chatgpt-tool-hub
Author: wqjuser
Author-email: wqjuser@gmail.com
License: MIT
Classifier: Intended Audience :: Developers
Classifier: Intended Audience :: Education
Classifier: License :: OSI Approved :: MIT License
Classifier: Programming Language :: Python :: 3.8
Classifier: Programming Language :: Python :: 3.9
Classifier: Programming Language :: Python :: 3.10
Classifier: Topic :: Software Development :: Libraries
Classifier: Topic :: Software Development :: Libraries :: Python Modules
License-File: LICENSE
Requires-Dist: pydantic (~=1.10.7)
Requires-Dist: pyopenssl
Requires-Dist: pyyaml (~=6.0)
Requires-Dist: lxml
Requires-Dist: beautifulsoup4 (~=4.12.0)
Requires-Dist: tenacity (~=8.2.2)
Requires-Dist: openai (~=0.28.1)
Requires-Dist: tiktoken (~=0.4.0)
Requires-Dist: arxiv
Requires-Dist: wikipedia
Requires-Dist: wolframalpha
Requires-Dist: aiohttp (~=3.8.4)
Requires-Dist: requests (~=2.28.2)
Requires-Dist: google-api-python-client
Requires-Dist: SQLAlchemy (~=2.0.7)
Requires-Dist: selenium
Requires-Dist: webdriver-manager
Requires-Dist: rich
